{
  "apiVersion": 2,
  "name": "oik/contact-form",
  "title": "Contact form",
  "category": "common",
  "icon": "forms",
  "description": "Displays a Contact form",
  "attributes": {
    "textAlign": {
      "type": "string"
    },
    "className": {
      "type": "string"
    },
    "textColor": {
      "type": "string"
    },
    "backgroundColor": {
      "type": "string"
    },
    "style": {
      "type": "object"
    },
    "fontSize": {
      "type": "string"
    },
    "gradient": {
      "type": "string"
    }
  },
  "supports": {
    "html": false,
    "customClassName": false,
    "className": false,
    "color": {
      "gradients": false,
      "text": false,
      "background": false,
      "link": false
    },
    "typography": {
      "fontSize": false,
      "lineHeight": false
    }
  },
  "keywords": [ "Contact", "form", "oik" ]
}